cuequivariance_torch/VERSION
cuequivariance_torch/__init__.py
cuequivariance_torch/benchmarking.py
cuequivariance_torch/_tests/__init__.py
cuequivariance_torch/_tests/utils.py
cuequivariance_torch/layers/__init__.py
cuequivariance_torch/layers/batchnorm.py
cuequivariance_torch/layers/tp_conv_fully_connected.py
cuequivariance_torch/operations/linear.py
cuequivariance_torch/operations/rotation.py
cuequivariance_torch/operations/spherical_harmonics.py
cuequivariance_torch/operations/symmetric_contraction.py
cuequivariance_torch/operations/tp_channel_wise.py
cuequivariance_torch/operations/tp_fully_connected.py
cuequivariance_torch/primitives/equivariant_tensor_product.py
cuequivariance_torch/primitives/segmented_polynomial.py
cuequivariance_torch/primitives/segmented_polynomial_fused_tp.py
cuequivariance_torch/primitives/segmented_polynomial_indexed_linear.py
cuequivariance_torch/primitives/segmented_polynomial_naive.py
cuequivariance_torch/primitives/segmented_polynomial_uniform_1d.py
cuequivariance_torch/primitives/symmetric_tensor_product.py
cuequivariance_torch/primitives/tensor_product.py
cuequivariance_torch/primitives/transpose.py
cuequivariance_torch/primitives/triangle.py
Third_party_attr.txt
cuequivariance_torch-0.8.1.dist-info/METADATA
cuequivariance_torch-0.8.1.dist-info/WHEEL
cuequivariance_torch-0.8.1.dist-info/licenses/LICENSE
cuequivariance_torch-0.8.1.dist-info/RECORD
